[{"name":"keyboard_plugin","qualifiedName":"keyboard_plugin","href":"keyboard_plugin/keyboard_plugin-library.html","type":"library","overriddenDepth":0},{"name":"KeyboardPlugin","qualifiedName":"keyboard_plugin.KeyboardPlugin","href":"keyboard_plugin/KeyboardPlugin-class.html","type":"class","overriddenDepth":0,"enclosedBy":{"name":"keyboard_plugin","type":"library"}},{"name":"KeyboardPlugin","qualifiedName":"keyboard_plugin.KeyboardPlugin","href":"keyboard_plugin/KeyboardPlugin/KeyboardPlugin.html","type":"constructor","overriddenDepth":0,"enclosedBy":{"name":"KeyboardPlugin","type":"class"}},{"name":"operator ==","qualifiedName":"keyboard_plugin.KeyboardPlugin.==","href":"keyboard_plugin/KeyboardPlugin/operator_equals.html","type":"method","overriddenDepth":0,"enclosedBy":{"name":"KeyboardPlugin","type":"class"}},{"name":"hashCode","qualifiedName":"keyboard_plugin.KeyboardPlugin.hashCode","href":"keyboard_plugin/KeyboardPlugin/hashCode.html","type":"property","overriddenDepth":0,"enclosedBy":{"name":"KeyboardPlugin","type":"class"}},{"name":"hide","qualifiedName":"keyboard_plugin.KeyboardPlugin.hide","href":"keyboard_plugin/KeyboardPlugin/hide.html","type":"method","overriddenDepth":0,"enclosedBy":{"name":"KeyboardPlugin","type":"class"}},{"name":"hideFormAccessoryBar","qualifiedName":"keyboard_plugin.KeyboardPlugin.hideFormAccessoryBar","href":"keyboard_plugin/KeyboardPlugin/hideFormAccessoryBar.html","type":"method","overriddenDepth":0,"enclosedBy":{"name":"KeyboardPlugin","type":"class"}},{"name":"isVisible","qualifiedName":"keyboard_plugin.KeyboardPlugin.isVisible","href":"keyboard_plugin/KeyboardPlugin/isVisible.html","type":"property","overriddenDepth":0,"enclosedBy":{"name":"KeyboardPlugin","type":"class"}},{"name":"keyboardDidHide","qualifiedName":"keyboard_plugin.KeyboardPlugin.keyboardDidHide","href":"keyboard_plugin/KeyboardPlugin/keyboardDidHide.html","type":"method","overriddenDepth":0,"enclosedBy":{"name":"KeyboardPlugin","type":"class"}},{"name":"keyboardDidShow","qualifiedName":"keyboard_plugin.KeyboardPlugin.keyboardDidShow","href":"keyboard_plugin/KeyboardPlugin/keyboardDidShow.html","type":"method","overriddenDepth":0,"enclosedBy":{"name":"KeyboardPlugin","type":"class"}},{"name":"keyboardWillHide","qualifiedName":"keyboard_plugin.KeyboardPlugin.keyboardWillHide","href":"keyboard_plugin/KeyboardPlugin/keyboardWillHide.html","type":"method","overriddenDepth":0,"enclosedBy":{"name":"KeyboardPlugin","type":"class"}},{"name":"keyboardWillShow","qualifiedName":"keyboard_plugin.KeyboardPlugin.keyboardWillShow","href":"keyboard_plugin/KeyboardPlugin/keyboardWillShow.html","type":"method","overriddenDepth":0,"enclosedBy":{"name":"KeyboardPlugin","type":"class"}},{"name":"noSuchMethod","qualifiedName":"keyboard_plugin.KeyboardPlugin.noSuchMethod","href":"keyboard_plugin/KeyboardPlugin/noSuchMethod.html","type":"method","overriddenDepth":0,"enclosedBy":{"name":"KeyboardPlugin","type":"class"}},{"name":"runtimeType","qualifiedName":"keyboard_plugin.KeyboardPlugin.runtimeType","href":"keyboard_plugin/KeyboardPlugin/runtimeType.html","type":"property","overriddenDepth":0,"enclosedBy":{"name":"KeyboardPlugin","type":"class"}},{"name":"show","qualifiedName":"keyboard_plugin.KeyboardPlugin.show","href":"keyboard_plugin/KeyboardPlugin/show.html","type":"method","overriddenDepth":0,"enclosedBy":{"name":"KeyboardPlugin","type":"class"}},{"name":"toString","qualifiedName":"keyboard_plugin.KeyboardPlugin.toString","href":"keyboard_plugin/KeyboardPlugin/toString.html","type":"method","overriddenDepth":0,"enclosedBy":{"name":"KeyboardPlugin","type":"class"}},{"name":"KeyboardPluginEvent","qualifiedName":"keyboard_plugin.KeyboardPluginEvent","href":"keyboard_plugin/KeyboardPluginEvent-class.html","type":"class","overriddenDepth":0,"enclosedBy":{"name":"keyboard_plugin","type":"library"}},{"name":"KeyboardPluginEvent","qualifiedName":"keyboard_plugin.KeyboardPluginEvent","href":"keyboard_plugin/KeyboardPluginEvent/KeyboardPluginEvent.html","type":"constructor","overriddenDepth":0,"enclosedBy":{"name":"KeyboardPluginEvent","type":"class"}},{"name":"operator ==","qualifiedName":"keyboard_plugin.KeyboardPluginEvent.==","href":"keyboard_plugin/KeyboardPluginEvent/operator_equals.html","type":"method","overriddenDepth":0,"enclosedBy":{"name":"KeyboardPluginEvent","type":"class"}},{"name":"hashCode","qualifiedName":"keyboard_plugin.KeyboardPluginEvent.hashCode","href":"keyboard_plugin/KeyboardPluginEvent/hashCode.html","type":"property","overriddenDepth":0,"enclosedBy":{"name":"KeyboardPluginEvent","type":"class"}},{"name":"keyboardHeight","qualifiedName":"keyboard_plugin.KeyboardPluginEvent.keyboardHeight","href":"keyboard_plugin/KeyboardPluginEvent/keyboardHeight.html","type":"property","overriddenDepth":0,"enclosedBy":{"name":"KeyboardPluginEvent","type":"class"}},{"name":"noSuchMethod","qualifiedName":"keyboard_plugin.KeyboardPluginEvent.noSuchMethod","href":"keyboard_plugin/KeyboardPluginEvent/noSuchMethod.html","type":"method","overriddenDepth":0,"enclosedBy":{"name":"KeyboardPluginEvent","type":"class"}},{"name":"runtimeType","qualifiedName":"keyboard_plugin.KeyboardPluginEvent.runtimeType","href":"keyboard_plugin/KeyboardPluginEvent/runtimeType.html","type":"property","overriddenDepth":0,"enclosedBy":{"name":"KeyboardPluginEvent","type":"class"}},{"name":"toString","qualifiedName":"keyboard_plugin.KeyboardPluginEvent.toString","href":"keyboard_plugin/KeyboardPluginEvent/toString.html","type":"method","overriddenDepth":0,"enclosedBy":{"name":"KeyboardPluginEvent","type":"class"}}]
